WaporTranslator/Run_LEVEL1.py
WaporTranslator/Run_LEVEL2.py
WaporTranslator/Run_LEVEL3.py
WaporTranslator/__init__.py
WaporTranslator/LEVEL_1/DataCube.py
WaporTranslator/LEVEL_1/Input_Data.py
WaporTranslator/LEVEL_1/LEVEL_1_AOI.py
WaporTranslator/LEVEL_1/LEVEL_1_Create_Mask.py
WaporTranslator/LEVEL_1/LEVEL_1_Download_ESACCI.py
WaporTranslator/LEVEL_1/LEVEL_1_Download_GLDAS.py
WaporTranslator/LEVEL_1/LEVEL_1_Download_MODIS.py
WaporTranslator/LEVEL_1/LEVEL_1_Download_SRTM.py
WaporTranslator/LEVEL_1/LEVEL_1_Download_SoilGrids.py
WaporTranslator/LEVEL_1/LEVEL_1_Download_WAPOR.py
WaporTranslator/LEVEL_1/LEVEL_1_Process_KNMI.py
WaporTranslator/LEVEL_1/LEVEL_1_Process_MSGCCP.py
WaporTranslator/LEVEL_1/Run_LEVEL1_old.py
WaporTranslator/LEVEL_1/__init__.py
WaporTranslator/LEVEL_2/Functions.py
WaporTranslator/LEVEL_2/Phenology.py
WaporTranslator/LEVEL_2/Run_Intermediate_Parameters.py
WaporTranslator/LEVEL_2/Run_LEVEL2_old.py
WaporTranslator/LEVEL_2/__init__.py
WaporTranslator/LEVEL_3/Run_LEVEL3_old.py
WaporTranslator/LEVEL_3/__init__.py
WaporTranslator/LEVEL_3/Climate_Smart/LEVEL_3_Calc_Climate_Smart.py
WaporTranslator/LEVEL_3/Climate_Smart/__init__.py
WaporTranslator/LEVEL_3/Drought/LEVEL_3_Calc_Drought.py
WaporTranslator/LEVEL_3/Drought/__init__.py
WaporTranslator/LEVEL_3/Food_Security/LEVEL_3_Calc_Food_Security.py
WaporTranslator/LEVEL_3/Food_Security/__init__.py
WaporTranslator/LEVEL_3/Irrigation/LEVEL_3_Calc_Irrigation.py
WaporTranslator/LEVEL_3/Irrigation/__init__.py
WaporTranslator/LEVEL_3/Water_Productivity/LEVEL_3_Calc_Water_Productivity.py
WaporTranslator/LEVEL_3/Water_Productivity/__init__.py
WaporTranslator-0.0.0.dist-info/LICENSE
WaporTranslator-0.0.0.dist-info/METADATA
WaporTranslator-0.0.0.dist-info/WHEEL
WaporTranslator-0.0.0.dist-info/top_level.txt
WaporTranslator-0.0.0.dist-info/RECORD
