Metadata-Version: 2.1
Name: WaporTranslator
Version: 0.0.0
Summary: Python module for calculating Climate, Drought, Food Security, Irrigation, and Water Productivity indicators mostly based on the FAO's WaPOR datasets.
Home-page: https://github.com/TimHessels/WaporTranslator
Author: Tim Hessels
Author-email: timhessels@hotmail.com
License: UNKNOWN
Platform: UNKNOWN
Classifier: Programming Language :: Python :: 3
Classifier: License :: OSI Approved :: Apache Software License
Classifier: Operating System :: OS Independent
